{
  "name": "Data Source Directory",
  "description": "The class Data Source Directory represents a specific directory for the management of source data.\n",
  "unique": false,
  "relationships": [
    {
      "start": "Data Source",
      "end": "Data Source Directory",
      "type": 3
    },
    {
      "start": "Data Source Directory",
      "end": "Building",
      "type": 3
    },
    {
      "start": "Data Source Directory",
      "end": "Directory",
      "type": 0
    },
    {
      "start": "Data Source Directory",
      "end": "Monitored Object",
      "type": 3
    },
    {
      "start": "FTP Server",
      "end": "Data Source Directory",
      "type": 3
    },
    {
      "start": "HTTP Server",
      "end": "Data Source Directory",
      "type": 3
    },
    {
      "start": "IMAP EMail Server",
      "end": "Data Source Directory",
      "type": 3
    },
    {
      "start": "Loytec XML-DL Server",
      "end": "Data Source Directory",
      "type": 3
    },
    {
      "start": "POP3 EMail Server",
      "end": "Data Source Directory",
      "type": 3
    },
    {
      "start": "sFTP Server",
      "end": "Data Source Directory",
      "type": 3
    },
    {
      "start": "SOAP Server",
      "end": "Data Source Directory",
      "type": 3
    },
    {
      "start": "VIDA350",
      "end": "Data Source Directory",
      "type": 3
    }
  ]
}
