{
  "name": "Pump",
  "description": "The class Pump contains data of the building equipment pump. Attributes of the class include a complete description of the specific energy data of the pump. ",
  "unique": false,
  "relationships": [
    {
      "start": "Pump",
      "end": "Building Equipment",
      "type": 0
    },
    {
      "start": "Pump",
      "end": "Heating Equipment Directory",
      "type": 3
    }
  ],
  "types": [
    {
      "name": "Domain",
      "primitiveType": 0,
      "guiType": "Text",
      "guiposition": 10,
      "validity": 0,
      "inherited": false,
      "jevisClass": "Pump"
    }
  ]
}
