{
  "name": "Energy Metering Point Operator",
  "description": "The class Energy Metering Point Operator defines non-specified attributes as a base class",
  "unique": false,
  "relationships": [
  ],
  "types": [
    {
      "name": "Contractor",
      "primitiveType": 0,
      "guiType": "Object Target",
      "guiposition": 0,
      "validity": 0,
      "inherited": false,
      "jevisClass": "Energy Metering Point Operator"
    },
    {
      "name": "Energy Metering Point Operator Code Number",
      "primitiveType": 0,
      "guiType": "Text",
      "guiposition": 11,
      "validity": 0,
      "inherited": false,
      "jevisClass": "Energy Metering Point Operator"
    },
    {
      "name": "Net Cost",
      "primitiveType": 1,
      "guiType": "Number with Unit",
      "guiposition": 17,
      "validity": 0,
      "inherited": false,
      "jevisClass": "Energy Metering Point Operator"
    },
    {
      "name": "Additional Relative Cost",
      "primitiveType": 1,
      "guiType": "Number with Unit",
      "guiposition": 98,
      "validity": 0,
      "inherited": false,
      "jevisClass": "Energy Metering Point Operator"
    },
    {
      "name": "Additional Fix Cost",
      "primitiveType": 1,
      "guiType": "Number with Unit",
      "guiposition": 99,
      "validity": 0,
      "inherited": false,
      "jevisClass": "Energy Metering Point Operator"
    }
  ]
}
